tortilla/__init__.py
tortilla/api.py
tortilla/cache.py
tortilla/formatters.py
tortilla/utils.py
tortilla/wrappers.py
tortilla-0.5.0.dist-info/METADATA
tortilla-0.5.0.dist-info/RECORD
tortilla-0.5.0.dist-info/WHEEL
tortilla-0.5.0.dist-info/top_level.txt
