Metadata-Version: 2.1
Name: tortilla
Version: 0.5.0
Summary: Wrapping web APIs made easy.
Home-page: https://github.com/tortilla/tortilla
Author: Hidde Bultsma
Author-email: me@redodo.io
License: MIT
Keywords: api wrapper
Platform: UNKNOWN
Classifier: Development Status :: 5 - Production/Stable
Classifier: Intended Audience :: Developers
Classifier: License :: OSI Approved :: MIT License
Classifier: Programming Language :: Python :: 2
Classifier: Programming Language :: Python :: 2.6
Classifier: Programming Language :: Python :: 2.7
Classifier: Programming Language :: Python :: 3
Classifier: Programming Language :: Python :: 3.3
Classifier: Programming Language :: Python :: 3.4
Classifier: Programming Language :: Python :: 3.5
Classifier: Programming Language :: Python :: 3.6
Classifier: Topic :: Internet
Requires-Dist: colorama
Requires-Dist: requests
Requires-Dist: formats
Requires-Dist: six
Requires-Dist: httpretty
